Metadata-Version: 1.1
Name: antlr3-python-runtime
Version: 3.4
Summary: Runtime package for ANTLR3
Home-page: http://www.antlr.org/
Author: Benjamin Niemann
Author-email: pink@odahoda.de
License: BSD
Download-URL: http://www.antlr.org/download.html
Platform: UNKNOWN
